[
  {
    "title": "any",
    "_id": "1",
    "comments": []
  },
  {
    "title": "new book",
    "_id": "2",
    "comments": []
  },
  {
    "title": "new book",
    "_id": "3",
    "comments": []
  },
  {
    "title": "new book",
    "_id": "4",
    "comments": []
  },
  {
    "title": "new book",
    "_id": "5",
    "comments": []
  },
  {
    "title": "new book",
    "_id": "6",
    "comments": []
  },
  {
    "title": "new book",
    "_id": "7",
    "comments": []
  },
  {
    "title": "new book",
    "_id": "9",
    "comments": []
  },
  {
    "title": "new book",
    "_id": "11",
    "comments": []
  },
  {
    "title": "new book",
    "_id": "12",
    "comments": []
  },
  {
    "title": "new book",
    "_id": "13",
    "comments": [
      "first comment"
    ]
  },
  {
    "title": "new book",
    "_id": "14",
    "comments": [
      "first comment",
      null
    ]
  },
  {
    "title": "new book",
    "_id": "15",
    "comments": [
      "first comment"
    ]
  },
  {
    "title": "new book",
    "_id": "16",
    "comments": [
      "first comment"
    ]
  },
  {
    "title": "new book",
    "_id": "17",
    "comments": [
      "first comment"
    ]
  },
  {
    "title": "new book",
    "_id": "18",
    "comments": [
      "first comment"
    ]
  },
  {
    "title": "new book",
    "_id": "19",
    "comments": [
      "first comment"
    ]
  },
  {
    "title": "new book",
    "_id": "20",
    "comments": [
      "first comment"
    ]
  },
  {
    "title": "new book",
    "_id": "21",
    "comments": [
      "first comment"
    ]
  },
  {
    "title": "new book",
    "_id": "22",
    "comments": [
      "first comment"
    ]
  },
  {
    "title": "new book",
    "_id": "23",
    "comments": [
      "first comment"
    ]
  },
  {
    "title": "new book",
    "_id": "24",
    "comments": [
      "first comment"
    ]
  },
  {
    "title": "new book",
    "_id": "25",
    "comments": [
      "first comment"
    ]
  },
  {
    "title": "vvvv",
    "_id": "26",
    "comments": []
  }
]